crowd4py/__init__.py
crowd4py/api.py
crowd4py/helpers.py
crowd4py/task.py
crowd4py-0.1.0.dist-info/DESCRIPTION.rst
crowd4py-0.1.0.dist-info/METADATA
crowd4py-0.1.0.dist-info/RECORD
crowd4py-0.1.0.dist-info/WHEEL
crowd4py-0.1.0.dist-info/metadata.json
crowd4py-0.1.0.dist-info/top_level.txt
sample/01_Phase1-algorithm-sample.py
sample/01_Phase2-algorithm-sample.py
sample/02_Phase1-ai-sample.py
sample/02_Phase2-ai-sample.py
sample/__init__.py
sample/utils/__init__.py
sample/utils/api.py
sample/workers/__init__.py
sample/workers/ai_worker.py
sample/workers/algorithm_worker.py
sample/workers/worker_base.py
