Metadata-Version: 2.0
Name: crowd4py
Version: 0.1.0
Summary: Crowd4u library for python
Home-page: https://github.com/SShayashi
Author: Masafumi Hayashi
Author-email: sshayashi0208@gmail.com
License: Copyright (c) 2017, Masafumi Hayashi
Requires-Dist: ConfigParser
Requires-Dist: requests
Requires-Dist: lxml
